pygame_gifs.py
pygame_gifs-1.0.0.dist-info/licenses/LICENSE
pygame_gifs-1.0.0.dist-info/METADATA
pygame_gifs-1.0.0.dist-info/WHEEL
pygame_gifs-1.0.0.dist-info/top_level.txt
pygame_gifs-1.0.0.dist-info/RECORD
