Metadata-Version: 2.4
Name: pygame-gifs
Version: 1.0.0
Summary: easily record gifs with pygame
Author-email: ScriptLine-Studios <scriptlinestudios@protonmail.com>
Project-URL: Homepage, https://github.com/ScriptLineStudios/pygame_gifs
Project-URL: Issues, https://github.com/ScriptLineStudios/pygame_gifs/issues
Classifier: Programming Language :: Python :: 3
Classifier: Operating System :: OS Independent
Classifier: License :: OSI Approved :: MIT License
Requires-Python: >=3.8
License-File: LICENSE
Dynamic: license-file
